CHANGES.rst
MANIFEST.in
README.rst
TODO.rst
setup.cfg
setup.py
imapIO/__init__.py
imapIO/tests.py
imapIO/utf_7_imap4.py
imapIO.egg-info/PKG-INFO
imapIO.egg-info/SOURCES.txt
imapIO.egg-info/dependency_links.txt
imapIO.egg-info/requires.txt
imapIO.egg-info/top_level.txt
imapIO.egg-info/zip-safe