Metadata-Version: 1.1
Name: imapIO
Version: 0.9.5
Summary: Convenience classes and methods for processing IMAP mailboxes
Home-page: https://github.com/invisibleroads/imapIO
Author: Roy Hyunjin Han
Author-email: service@invisibleroads.com
License: MIT
Keywords: imap
Platform: UNKNOWN
Classifier: Intended Audience :: Developers
Classifier: Programming Language :: Python
Classifier: License :: OSI Approved :: MIT License
